pygeoflood/__init__.py
pygeoflood/pygeoflood.py
pygeoflood/tools.py
pygeoflood/data/COMID_Roughness.csv
pygeoflood-0.0.2.dist-info/LICENSE
pygeoflood-0.0.2.dist-info/METADATA
pygeoflood-0.0.2.dist-info/WHEEL
pygeoflood-0.0.2.dist-info/top_level.txt
pygeoflood-0.0.2.dist-info/RECORD
