Metadata-Version: 2.1
Name: pygeoflood
Version: 0.0.2
Summary: Flood mapping program based on high-resolution terrain analyses
Author-email: Paola Passalacqua <paola@austin.utexas.edu>, Xing Zheng <zhengxingwhu@gmail.com>, Alec Carruthers <author@example.com>, Mark Wang <mark.wang@utexas.edu>, Matthew Preisser <mattpreisser@gmail.com>
Maintainer-email: Mark Wang <mark.wang@utexas.edu>, Matthew Preisser <mattpreisser@gmail.com>, Paola Passalacqua <paola@austin.utexas.edu>
Project-URL: Homepage, https://github.com/passaH2O/GeoFlood
Project-URL: Repository, https://github.com/passaH2O/GeoFlood
Project-URL: Bug Tracker, https://github.com/passaH2O/GeoFlood/issues
Classifier: Programming Language :: Python :: 3
Classifier: License :: OSI Approved :: GNU General Public License v3 (GPLv3)
Classifier: Operating System :: OS Independent
Requires-Python: <3.13,>=3.10
License-File: LICENSE
Requires-Dist: geopandas
Requires-Dist: ipykernel
Requires-Dist: matplotlib
Requires-Dist: numba
Requires-Dist: numpy
Requires-Dist: pandas
Requires-Dist: rasterio
Requires-Dist: scikit-fmm
Requires-Dist: scikit-image
Requires-Dist: scipy
Requires-Dist: whitebox
Requires-Dist: xarray
Requires-Dist: fiona
